CHANGES.txt
LICENSE.txt
MANIFEST.in
README.txt
setup.py
Image2Dia.egg-info/PKG-INFO
Image2Dia.egg-info/SOURCES.txt
Image2Dia.egg-info/dependency_links.txt
Image2Dia.egg-info/top_level.txt
bin/addImage2dia.py
bin/clic.png
bin/icon.png
bin/image2dia.png
bin/img2diagui.py
docs/doc.txt
image2dia/__init__.py
image2dia/image2dia.py