Metadata-Version: 1.0
Name: Image2Dia
Version: 0.51
Summary: Insert images into diagram editor Dia
Home-page: http://code.google.com/p/image2dia/
Author: Xavier Sala (utrescu)
Author-email: UNKNOWN
License: GPL
Platform: UNKNOWN
